LICENSE
MANIFEST.in
README.rst
setup.py
bitwise/__init__.py
bitwise/_version.py
bitwise.egg-info/PKG-INFO
bitwise.egg-info/SOURCES.txt
bitwise.egg-info/dependency_links.txt
bitwise.egg-info/not-zip-safe
bitwise.egg-info/top_level.txt
bitwise/arithmetic/ADD.py
bitwise/arithmetic/ADD_SUB.py
bitwise/arithmetic/MULT.py
bitwise/arithmetic/__init__.py
bitwise/gate/AND.py
bitwise/gate/BUF.py
bitwise/gate/IMPLY.py
bitwise/gate/NAND.py
bitwise/gate/NOR.py
bitwise/gate/NOT.py
bitwise/gate/OR.py
bitwise/gate/XNOR.py
bitwise/gate/XOR.py
bitwise/gate/__init__.py
bitwise/logic/AND.py
bitwise/logic/COMP.py
bitwise/logic/NAND.py
bitwise/logic/NOR.py
bitwise/logic/NOT.py
bitwise/logic/OR.py
bitwise/logic/PAR.py
bitwise/logic/XNOR.py
bitwise/logic/XOR.py
bitwise/logic/__init__.py
bitwise/processor/ALU.py
bitwise/processor/FLAG.py
bitwise/processor/PC.py
bitwise/processor/SP.py
bitwise/processor/__init__.py
bitwise/signal/DEC.py
bitwise/signal/DEMUX.py
bitwise/signal/ENC.py
bitwise/signal/INV_CTRL.py
bitwise/signal/MUX.py
bitwise/signal/SSD.py
bitwise/signal/__init__.py
bitwise/state/COUNT.py
bitwise/state/PISO.py
bitwise/state/RING.py
bitwise/state/SHIFT.py
bitwise/state/SIPO.py
bitwise/state/__init__.py
bitwise/storage/FLOP.py
bitwise/storage/RAM.py
bitwise/storage/REG.py
bitwise/storage/__init__.py
bitwise/wire/BUS.py
bitwise/wire/CLK.py
bitwise/wire/TRI.py
bitwise/wire/TRI_BUS.py
bitwise/wire/WIRE.py
bitwise/wire/__init__.py