Metadata-Version: 1.1
Name: bitwise
Version: 1.0
Summary: Bitwise is a library for utilizing Python as a hardware description language
Home-page: https://github.com/jamesjiang52/Bitwise
Author: James Jiang
Author-email: jamesjiang52@gmail.com
License: MIT
Keywords: bitwise hardware design
Platform: UNKNOWN
Classifier: Development Status :: 5 - Production/Stable
Classifier: License :: OSI Approved :: MIT License
Classifier: Natural Language :: English
Classifier: Operating System :: OS Independent
Classifier: Programming Language :: Python :: 3
Classifier: Topic :: Scientific/Engineering
Classifier: Topic :: Software Development :: Libraries :: Python Modules
